mltest/__init__.py
mltest/mltest.py
mltest/test_mltest.py
mltest-0.0.5.dist-info/DESCRIPTION.rst
mltest-0.0.5.dist-info/METADATA
mltest-0.0.5.dist-info/RECORD
mltest-0.0.5.dist-info/WHEEL
mltest-0.0.5.dist-info/metadata.json
mltest-0.0.5.dist-info/top_level.txt
