Metadata-Version: 2.0
Name: mltest
Version: 0.0.5
Summary: UNKNOWN
Home-page: UNKNOWN
Author: Chase Roberts
Author-email: keeper6928@gmail.com
License: MIT
Platform: UNKNOWN
Requires-Dist: tensorflow
Requires-Dist: numpy
